choppa/__init__.py
choppa/_internal.py
choppa/_version.py
choppa/artifacts.py
choppa/choppa.py
choppa/codegen.py
choppa/errors.py
choppa/py.typed
choppa/session.py
choppa-0.1.0.dist-info/METADATA
choppa-0.1.0.dist-info/WHEEL
choppa-0.1.0.dist-info/licenses/LICENSE
choppa-0.1.0.dist-info/RECORD
