Metadata-Version: 2.4
Name: choppa
Version: 0.1.0
Summary: Get to da cluster! Remote function execution for Databricks.
Project-URL: Homepage, https://github.com/callicrate/choppa
Project-URL: Repository, https://github.com/callicrate/choppa.git
Project-URL: Issues, https://github.com/callicrate/choppa/issues
Author: callicrate
License: MIT
License-File: LICENSE
Keywords: cluster,databricks,execution,remote,spark
Classifier: Development Status :: 4 - Beta
Classifier: Intended Audience :: Developers
Classifier: License :: OSI Approved :: MIT License
Classifier: Operating System :: OS Independent
Classifier: Programming Language :: Python :: 3
Classifier: Programming Language :: Python :: 3.10
Classifier: Programming Language :: Python :: 3.11
Classifier: Programming Language :: Python :: 3.12
Classifier: Topic :: Software Development :: Libraries :: Python Modules
Classifier: Typing :: Typed
Requires-Python: >=3.10
Requires-Dist: databricks-sdk>=0.20.0
Provides-Extra: dev
Requires-Dist: cloudpickle>=2.0.0; extra == 'dev'
Requires-Dist: mypy>=1.0.0; extra == 'dev'
Requires-Dist: pytest-cov>=4.0.0; extra == 'dev'
Requires-Dist: pytest>=7.0.0; extra == 'dev'
Requires-Dist: ruff>=0.4.0; extra == 'dev'
Provides-Extra: pickle
Requires-Dist: cloudpickle>=2.0.0; extra == 'pickle'
